pyRDDLGym_jax/__init__.py
pyRDDLGym_jax/entry_point.py
pyRDDLGym_jax/core/__init__.py
pyRDDLGym_jax/core/compiler.py
pyRDDLGym_jax/core/logic.py
pyRDDLGym_jax/core/model.py
pyRDDLGym_jax/core/planner.py
pyRDDLGym_jax/core/simulator.py
pyRDDLGym_jax/core/tuning.py
pyRDDLGym_jax/core/visualization.py
pyRDDLGym_jax/core/assets/__init__.py
pyRDDLGym_jax/core/assets/favicon.ico
pyRDDLGym_jax/examples/__init__.py
pyRDDLGym_jax/examples/run_gradient.py
pyRDDLGym_jax/examples/run_gym.py
pyRDDLGym_jax/examples/run_plan.py
pyRDDLGym_jax/examples/run_scipy.py
pyRDDLGym_jax/examples/run_tune.py
pyRDDLGym_jax/examples/configs/Cartpole_Continuous_gym_drp.cfg
pyRDDLGym_jax/examples/configs/Cartpole_Continuous_gym_replan.cfg
pyRDDLGym_jax/examples/configs/Cartpole_Continuous_gym_slp.cfg
pyRDDLGym_jax/examples/configs/HVAC_ippc2023_drp.cfg
pyRDDLGym_jax/examples/configs/HVAC_ippc2023_slp.cfg
pyRDDLGym_jax/examples/configs/MountainCar_Continuous_gym_slp.cfg
pyRDDLGym_jax/examples/configs/MountainCar_ippc2023_slp.cfg
pyRDDLGym_jax/examples/configs/PowerGen_Continuous_drp.cfg
pyRDDLGym_jax/examples/configs/PowerGen_Continuous_replan.cfg
pyRDDLGym_jax/examples/configs/PowerGen_Continuous_slp.cfg
pyRDDLGym_jax/examples/configs/Quadcopter_drp.cfg
pyRDDLGym_jax/examples/configs/Quadcopter_slp.cfg
pyRDDLGym_jax/examples/configs/Reservoir_Continuous_drp.cfg
pyRDDLGym_jax/examples/configs/Reservoir_Continuous_replan.cfg
pyRDDLGym_jax/examples/configs/Reservoir_Continuous_slp.cfg
pyRDDLGym_jax/examples/configs/UAV_Continuous_slp.cfg
pyRDDLGym_jax/examples/configs/Wildfire_MDP_ippc2014_drp.cfg
pyRDDLGym_jax/examples/configs/Wildfire_MDP_ippc2014_replan.cfg
pyRDDLGym_jax/examples/configs/Wildfire_MDP_ippc2014_slp.cfg
pyRDDLGym_jax/examples/configs/__init__.py
pyRDDLGym_jax/examples/configs/default_drp.cfg
pyRDDLGym_jax/examples/configs/default_replan.cfg
pyRDDLGym_jax/examples/configs/default_slp.cfg
pyRDDLGym_jax/examples/configs/tuning_drp.cfg
pyRDDLGym_jax/examples/configs/tuning_replan.cfg
pyrddlgym_jax-2.8.dist-info/licenses/LICENSE
pyrddlgym_jax-2.8.dist-info/METADATA
pyrddlgym_jax-2.8.dist-info/WHEEL
pyrddlgym_jax-2.8.dist-info/entry_points.txt
pyrddlgym_jax-2.8.dist-info/top_level.txt
pyrddlgym_jax-2.8.dist-info/RECORD
