Metadata-Version: 2.4
Name: pyRDDLGym-jax
Version: 2.8
Summary: pyRDDLGym-jax: automatic differentiation for solving sequential planning problems in JAX.
Home-page: https://github.com/pyrddlgym-project/pyRDDLGym-jax
Author: Michael Gimelfarb, Ayal Taitler, Scott Sanner
Author-email: mike.gimelfarb@mail.utoronto.ca, ataitler@gmail.com, ssanner@mie.utoronto.ca
License: MIT License
Classifier: Development Status :: 5 - Production/Stable
Classifier: Intended Audience :: Science/Research
Classifier: License :: OSI Approved :: MIT License
Classifier: Natural Language :: English
Classifier: Operating System :: OS Independent
Classifier: Programming Language :: Python :: 3
Classifier: Programming Language :: Python :: 3.9
Classifier: Programming Language :: Python :: 3.10
Classifier: Programming Language :: Python :: 3.11
Classifier: Programming Language :: Python :: 3.12
Classifier: Topic :: Scientific/Engineering :: Artificial Intelligence
Requires-Python: >=3.9
License-File: LICENSE
Requires-Dist: pyRDDLGym>=2.5
Requires-Dist: tqdm>=4.66
Requires-Dist: jax>=0.4.12
Requires-Dist: optax>=0.1.9
Requires-Dist: dm-haiku>=0.0.10
Requires-Dist: tensorflow-probability>=0.21.0
Provides-Extra: extra
Requires-Dist: bayesian-optimization>=2.0.0; extra == "extra"
Requires-Dist: rddlrepository>=2.0; extra == "extra"
Provides-Extra: dashboard
Requires-Dist: dash>=2.18.0; extra == "dashboard"
Requires-Dist: dash-bootstrap-components>=1.6.0; extra == "dashboard"
Dynamic: author
Dynamic: author-email
Dynamic: classifier
Dynamic: description
Dynamic: description-content-type
Dynamic: home-page
Dynamic: license
Dynamic: license-file
Dynamic: provides-extra
Dynamic: requires-dist
Dynamic: requires-python
Dynamic: summary
